renren_mall/__init__.py
RenRenMall-0.1.0.dist-info/LICENSE
RenRenMall-0.1.0.dist-info/METADATA
RenRenMall-0.1.0.dist-info/WHEEL
RenRenMall-0.1.0.dist-info/top_level.txt
RenRenMall-0.1.0.dist-info/RECORD
