Metadata-Version: 2.1
Name: RenRenMall
Version: 0.1.0
Summary: 人人商城后台管理
Author: YarnBlue
Author-email: zqb090325@126.com
License: UNKNOWN
Platform: UNKNOWN
License-File: LICENSE
